base64NoUpperCase/__init__.py
base64_no_upper_case-0.0.1.dist-info/licenses/LICENSE.txt
base64_no_upper_case-0.0.1.dist-info/METADATA
base64_no_upper_case-0.0.1.dist-info/WHEEL
base64_no_upper_case-0.0.1.dist-info/top_level.txt
base64_no_upper_case-0.0.1.dist-info/RECORD
