Metadata-Version: 2.4
Name: base64-no-upper-case
Version: 0.0.1
Summary: Base64, but no UPPER CASE.
Author: bddjr
License-Expression: Unlicense
Project-URL: Source, https://github.com/bddjr/base64-no-upper-case-py
Keywords: base64,scratch,upper,lower,case,uppercase,lowercase,encode,decode
Classifier: Programming Language :: Python :: 3
Classifier: Operating System :: OS Independent
Requires-Python: >=3.0
License-File: LICENSE.txt
Dynamic: license-file
